llm_gemini_youtube.py
llm_gemini_youtube-0.0.3.dist-info/licenses/LICENSE
llm_gemini_youtube-0.0.3.dist-info/METADATA
llm_gemini_youtube-0.0.3.dist-info/WHEEL
llm_gemini_youtube-0.0.3.dist-info/entry_points.txt
llm_gemini_youtube-0.0.3.dist-info/top_level.txt
llm_gemini_youtube-0.0.3.dist-info/RECORD
