Metadata-Version: 2.4
Name: llm-gemini-youtube
Version: 0.0.3
Summary: LLM plugin to access Google's Gemini family of models, with support for YouTube URLs
Author-email: nikkie <takuyafjp+develop@gmail.com>
License-Expression: Apache-2.0
Project-URL: Homepage, https://github.com/ftnext/llm-gemini-youtube
Project-URL: Changelog, https://github.com/ftnext/llm-gemini-youtube/releases
Project-URL: Issues, https://github.com/ftnext/llm-gemini-youtube/issues
Project-URL: CI, https://github.com/ftnext/llm-gemini-youtube/actions
Classifier: Development Status :: 1 - Planning
Classifier: Intended Audience :: Developers
Classifier: Intended Audience :: End Users/Desktop
Classifier: Intended Audience :: Science/Research
Classifier: Programming Language :: Python :: 3
Classifier: Programming Language :: Python :: 3.10
Classifier: Programming Language :: Python :: 3.11
Classifier: Programming Language :: Python :: 3.12
Classifier: Programming Language :: Python :: 3.13
Classifier: Programming Language :: Python :: 3.14
Classifier: Topic :: Scientific/Engineering :: Artificial Intelligence
Classifier: Topic :: Text Processing :: Linguistic
Classifier: Topic :: Utilities
Requires-Python: >=3.10
License-File: LICENSE
Requires-Dist: llm
Requires-Dist: google-genai
Provides-Extra: test
Requires-Dist: pytest; extra == "test"
Dynamic: license-file
